{
  "configurations": [
    {
      "name": "Wii DevKitPPC",
      "includePath": [
        "${workspaceFolder}/**",
        "D:/devkitPro/libogc/include",
        "D:/devkitPro/libogc/include/wiiuse",
        "D:/devkitPro/portlibs/wii/include",
        "D:/devkitPro/portlibs/ppc/include",
        "D:/devkitPro/GRRLIB/**"
      ],
      "defines": [
        "__WII__",
        "_DEBUG"
      ],
      "compilerPath": "D:/devkitPro/devkitPPC/bin/powerpc-eabi-gcc.exe",
      "cStandard": "c11",
      "cppStandard": "gnu++17",
      "intelliSenseMode": "gcc-x64"
    }
  ],
  "version": 4
}